rust_sasa_python/__init__.py
rust_sasa_python/__init__.pyi
rust_sasa_python/py.typed
rust_sasa_python/rust_sasa_python.cpython-313-darwin.so
rust_sasa_python-0.7.2.dist-info/METADATA
rust_sasa_python-0.7.2.dist-info/WHEEL
rust_sasa_python-0.7.2.dist-info/licenses/LICENSE.md
rust_sasa_python-0.7.2.dist-info/RECORD
