Metadata-Version: 2.4
Name: rust-sasa-python
Version: 0.7.2
Classifier: Programming Language :: Rust
Classifier: Programming Language :: Python :: Implementation :: CPython
Classifier: Programming Language :: Python :: Implementation :: PyPy
Requires-Dist: pytest>=8.4.1 ; extra == 'dev'
Requires-Dist: maturin>=1.5,<2.0 ; extra == 'dev'
Provides-Extra: dev
License-File: LICENSE.md
Summary: An ultra-fast package for computing Solvent Accessible Surface Area (SASA/ASA) for proteins
Author: Max Campbell
Requires-Python: >=3.11
